{
  "asteroid" : [{
      "lives" : 1,
      "moveX" : -0.510196,
      "moveY" : 1.000000,
      "x" : 458.051636,
      "y" : 699.689697
    }, {
      "lives" : 1,
      "moveX" : 0.943782,
      "moveY" : 1.000000,
      "x" : 903.370422,
      "y" : 499.652618
    }, {
      "lives" : 1,
      "moveX" : 0.360518,
      "moveY" : 1.000000,
      "x" : 691.888977,
      "y" : 99.562279
    }],
  "asteroidBig" : [{
      "lives" : 4,
      "moveX" : 0.512071,
      "moveY" : 1.000000,
      "x" : 997.040527,
      "y" : 696.614624
    }, {
      "lives" : 5,
      "moveX" : -0.938784,
      "moveY" : 1.000000,
      "x" : -287.827301,
      "y" : 396.640717
    }, {
      "lives" : 5,
      "moveX" : 0.587721,
      "moveY" : 1.000000,
      "x" : 1165.823120,
      "y" : 96.558746
    }],
  "enemyA" : [{
      "lives" : 2,
      "moveX" : 0.000000,
      "moveY" : 1.000000,
      "x" : 822.523071,
      "y" : 212.507080
    }],
  "enemyB" : [{
      "lives" : 3,
      "moveX" : 1.000000,
      "moveY" : 1.000000,
      "x" : 902.281128,
      "y" : 55.520542
    }],
  "enemyLaserA" : [{
      "lives" : 1,
      "moveX" : 0.000000,
      "moveY" : 1.000000,
      "x" : 854.403687,
      "y" : 5006.702637
    }, {
      "lives" : 1,
      "moveX" : 0.000000,
      "moveY" : 1.000000,
      "x" : 818.093506,
      "y" : 4221.955566
    }, {
      "lives" : 1,
      "moveX" : 0.000000,
      "moveY" : 1.000000,
      "x" : 854.403687,
      "y" : 4406.654297
    }, {
      "lives" : 1,
      "moveX" : 0.000000,
      "moveY" : 1.000000,
      "x" : 854.403687,
      "y" : 3655.405273
    }, {
      "lives" : 1,
      "moveX" : 0.000000,
      "moveY" : 1.000000,
      "x" : 818.093506,
      "y" : 3459.229492
    }, {
      "lives" : 1,
      "moveX" : 0.000000,
      "moveY" : 1.000000,
      "x" : 818.093506,
      "y" : 2859.184326
    }, {
      "lives" : 1,
      "moveX" : 0.000000,
      "moveY" : 1.000000,
      "x" : 822.523071,
      "y" : 394.115326
    }],
  "enemyLaserB" : [{
      "angle" : 40.889397,
      "lives" : 1,
      "moveX" : -0.654601,
      "moveY" : 0.755975,
      "x" : -1830.957764,
      "y" : 3076.784668
    }, {
      "angle" : 43.577595,
      "lives" : 1,
      "moveX" : -0.689336,
      "moveY" : 0.724441,
      "x" : -2104.779541,
      "y" : 3137.308838
    }, {
      "angle" : 72.037971,
      "lives" : 1,
      "moveX" : -0.951261,
      "moveY" : 0.308387,
      "x" : -2013.988647,
      "y" : 1391.877686
    }, {
      "angle" : 61.268856,
      "lives" : 1,
      "moveX" : -0.876885,
      "moveY" : 0.480700,
      "x" : -1607.659180,
      "y" : 1721.776001
    }, {
      "angle" : -264.944092,
      "lives" : 1,
      "moveX" : -0.996109,
      "moveY" : -0.088128,
      "x" : -1374.717407,
      "y" : 255.671936
    }, {
      "angle" : 40.296841,
      "lives" : 1,
      "moveX" : -0.646748,
      "moveY" : 0.762704,
      "x" : 91.261810,
      "y" : 850.716125
    }, {
      "angle" : 60.215767,
      "lives" : 1,
      "moveX" : -0.867902,
      "moveY" : 0.496735,
      "x" : 691.795471,
      "y" : 175.988831
    }],
  "highScore" : 5,
  "laser" : [{
      "moveX" : 0.000000,
      "moveY" : 0.000000,
      "x" : 252.940262,
      "y" : 30.946783
    }, {
      "moveX" : 0.000000,
      "moveY" : 0.000000,
      "x" : 273.551636,
      "y" : 247.946426
    }, {
      "moveX" : 0.000000,
      "moveY" : 0.000000,
      "x" : 330.632507,
      "y" : 328.076660
    }],
  "player" : {
    "lives" : 2,
    "x" : 330.633850,
    "y" : 427.164459
  },
  "score" : 5
}